.coveragerc
.gitlab-ci.yml
.pre-commit-config.yaml
AUTHORS.rst
CHANGES.rst
Dockerfile
LICENSE.txt
README.rst
requirements.txt
setup.cfg
setup.py
setup.sh
test-requirements.txt
tox.ini
antikythera/__init__.py
antikythera/antikythera.py
antikythera/capture.py
antikythera/cli.py
antikythera/decoder.py
antikythera/gui.py
antikythera/kivylogs.py
antikythera/metrics.py
antikythera/pysharkpatch.py
antikythera.egg-info/PKG-INFO
antikythera.egg-info/SOURCES.txt
antikythera.egg-info/dependency_links.txt
antikythera.egg-info/entry_points.txt
antikythera.egg-info/not-zip-safe
antikythera.egg-info/requires.txt
antikythera.egg-info/top_level.txt
antikythera/packets/__init__.py
antikythera/packets/assign.py
antikythera/packets/factory.py
antikythera/packets/packet.py
antikythera/packets/page.py
antikythera/packets/system.py
docs/Makefile
docs/authors.rst
docs/changes.rst
docs/conf.py
docs/index.rst
docs/license.rst
docs/_static/.gitignore
public/.gitkeep
tests/conftest.py
tests/test_cli_parser.py
tests/test_packets_factory.py
tests/test_data/intercepting_catcher.bin
tests/test_data/intercepting_catcher.pcap
tests/test_data/silent_sms.bin
tests/test_data/silent_sms.pcap
tests/test_data/tracking_catcher.bin
tests/test_data/tracking_catcher.pcap