Metadata-Version: 1.1
Name: antikythera
Version: 0.0.0
Summary: IMSI catcher detector
Home-page: https://gitlab.com/finding-ray/antikythera
Author: Derek Goddeau
Author-email: dgodd001@odu.edu
License: gpl3
Platform: UNKNOWN
Classifier: Development Status :: 3 - Alpha
Classifier: Environment :: X11 Applications
Classifier: License :: OSI Approved :: GNU General Public License v3 or later (GPLv3+)
Classifier: Natural Language :: English
Classifier: Operating System :: OS Independent
Classifier: Programming Language :: Python :: 3
Classifier: Topic :: Security
Classifier: Topic :: System :: Networking :: Monitoring
